sonagent/__init__.py
sonagent/__main__.py
sonagent/agent.py
sonagent/constants.py
sonagent/exceptions.py
sonagent/main.py
sonagent/sonbot.py
sonagent/version.py
sonagent/worker.py
sonagent/cell/__init__.py
sonagent/cell/cell.py
sonagent/commands/__init__.py
sonagent/commands/arguments.py
sonagent/commands/cli_options.py
sonagent/commands/run_commands.py
sonagent/configuration/__init__.py
sonagent/configuration/detect_environment.py
sonagent/configuration/load_config.py
sonagent/enums/__init__.py
sonagent/enums/enums.py
sonagent/enums/rpcmessagetype.py
sonagent/immune/__init__.py
sonagent/immune/immune.py
sonagent/immune/killer_t.py
sonagent/loggers/__init__.py
sonagent/loggers/buffering_handler.py
sonagent/loggers/logging_mixin.py
sonagent/loggers/set_log_levels.py
sonagent/loggers/std_err_stream_handler.py
sonagent/nerve_system/__init__.py
sonagent/nerve_system/brain.py
sonagent/nerve_system/brain_lobe.py
sonagent/nerve_system/nerve.py
sonagent/nerve_system/stimulus.py
sonagent/nerve_system/thalamus.py
sonagent/nerve_system/language_area/__init__.py
sonagent/nerve_system/language_area/claude.py
sonagent/nerve_system/language_area/gemini.py
sonagent/nerve_system/language_area/gpt.py
sonagent/nerve_system/language_area/llama.py
sonagent/nerve_system/language_area/llm_brain.py
sonagent/nerve_system/language_area/utils.py
sonagent/nerve_system/language_area/coding/__init__.py
sonagent/nerve_system/language_area/coding/gencode.py
sonagent/nerve_system/language_area/coding/sonautogen.py
sonagent/nerve_system/language_area/coding/utils.py
sonagent/nerve_system/language_area/prompt/__init__.py
sonagent/nerve_system/language_area/prompt/coding.py
sonagent/nerve_system/language_area/prompt/me.py
sonagent/nerve_system/language_area/prompt/planning.py
sonagent/nerve_system/language_area/prompt/schedule.py
sonagent/nerve_system/language_area/prompt/summary.py
sonagent/nerve_system/memory_area/__init__.py
sonagent/nerve_system/memory_area/memory.py
sonagent-1.0.13.dist-info/LICENSE
sonagent-1.0.13.dist-info/METADATA
sonagent-1.0.13.dist-info/WHEEL
sonagent-1.0.13.dist-info/entry_points.txt
sonagent-1.0.13.dist-info/top_level.txt
sonagent-1.0.13.dist-info/RECORD
