Metadata-Version: 2.1
Name: sonagent
Version: 1.0.13
Summary: Autonomous Agent for Digital Consciousness Backup Using Large Language Models (LLM).
Home-page: https://github.com/sonnhfit/sonagent
Author: Son Nguyen Huu
Author-email: sonnhfit@gmail.com
License: MIT
Keywords: agent ai ml language-model autonomus-robots large-language-models llm chatgpt llama2
Classifier: Programming Language :: Python :: 3.11
Classifier: Programming Language :: Python :: 3.12
Requires-Python: >=3.9.0
License-File: LICENSE
Requires-Dist: chromadb ==0.4.20
Requires-Dist: SQLAlchemy ==2.0.23
Requires-Dist: python-telegram-bot ==20.7
Requires-Dist: arrow ==1.3.0
Requires-Dist: fastapi ==0.108.0
Requires-Dist: pydantic ==2.5.3
Requires-Dist: uvicorn ==0.25.0
Requires-Dist: pyjwt ==2.8.0
Requires-Dist: aiofiles ==23.2.1
Requires-Dist: psutil ==5.9.7
Requires-Dist: python-rapidjson ==1.14
Requires-Dist: orjson ==3.9.10
Requires-Dist: sdnotify ==0.3.2
Requires-Dist: GitPython ==3.1.42
Requires-Dist: pyautogen ==0.2.15
Requires-Dist: schedule ==1.2.1
Requires-Dist: croniter ==2.0.3
Requires-Dist: tabulate ==0.9.0
